{
  "project_info": {
    "project_number": "685309146200",
    "project_id": "stb-cabs",
    "storage_bucket": "stb-cabs.appspot.com"
  },
  "client": [
    {
      "client_info": {
        "mobilesdk_app_id": "1:685309146200:android:ed77a692857b8175d4c62d",
        "android_client_info": {
          "package_name": "com.stbcabs.cabs"
        }
      },
      "oauth_client": [
        {
          "client_id": "685309146200-nebpmob4a3ovkdlgbbma56mbou37t3lp.apps.googleusercontent.com",
          "client_type": 3
        }
      ],
      "api_key": [
        {
          "current_key": "AIzaSyBBCVbMlBD0TsWIN51S3G6RbSVs6auMyGk"
        }
      ],
      "services": {
        "appinvite_service": {
          "other_platform_oauth_client": [
            {
              "client_id": "685309146200-nebpmob4a3ovkdlgbbma56mbou37t3lp.apps.googleusercontent.com",
              "client_type": 3
            },
            {
              "client_id": "685309146200-7nb4ppobfvkieitlh5fndvbb2m7sumhu.apps.googleusercontent.com",
              "client_type": 2,
              "ios_info": {
                "bundle_id": "com.stbcabs.cabs"
              }
            }
          ]
        }
      }
    }
  ],
  "configuration_version": "1"
}